{
  "required": true,
  "minVersion": "0.8",
  "package": "traben.emissive_entities.mixin",
  "compatibilityLevel": "JAVA_17",
  "mixins": [
    "accessor.ACC_LivingEntityRenderer",
    "client.entity.multitexture.MIX_AxolotlEntityRenderer",
    "client.entity.multitexture.MIX_BeeEntityRenderer",
    "client.entity.multitexture.MIX_CatEntityRenderer",
    "client.entity.multitexture.MIX_DonkeyEntityRenderer",
    "client.entity.multitexture.MIX_DrownedEntityRenderer",
    "client.entity.multitexture.MIX_FoxEntityRenderer",
    "client.entity.multitexture.MIX_GhastEntityRenderer",
    "client.entity.multitexture.MIX_HorseEntityRenderer",
    "client.entity.multitexture.MIX_LlamaEntityRenderer",
    "client.entity.multitexture.MIX_MooshroomEntityRenderer",
    "client.entity.multitexture.MIX_PandaEntityRenderer",
    "client.entity.multitexture.MIX_ParrotEntityRenderer",
    "client.entity.multitexture.MIX_PiglinEntityRenderer",
    "client.entity.multitexture.MIX_RabbitEntityRenderer",
    "client.entity.multitexture.MIX_ShulkerEntityRenderer",
    "client.entity.multitexture.MIX_StriderEntityRenderer",
    "client.entity.multitexture.MIX_VexEntityRenderer",
    "client.entity.multitexture.MIX_WitherEntityRenderer",
    "client.entity.multitexture.MIX_WolfEntityRenderer",
    "client.entity.multitexture.MIX_ZombieHorseEntityRenderer",
    "client.entity.singletexture.MIX_BatEntityRenderer",
    "client.entity.singletexture.MIX_CaveSpiderEntityRenderer",
    "client.entity.singletexture.MIX_ChickenEntityRenderer",
    "client.entity.singletexture.MIX_CodEntityRenderer",
    "client.entity.singletexture.MIX_CowEntityRenderer",
    "client.entity.singletexture.MIX_CreeperEntityRenderer",
    "client.entity.singletexture.MIX_DolphinEntityRenderer",
    "client.entity.singletexture.MIX_ElderGuardianEntityRenderer",
    "client.entity.singletexture.MIX_EndermiteEntityRenderer",
    "client.entity.singletexture.MIX_EvokerEntityRenderer",
    "client.entity.singletexture.MIX_GiantEntityRenderer",
    "client.entity.singletexture.MIX_GoatEntityRenderer",
    "client.entity.singletexture.MIX_GuardianEntityRenderer",
    "client.entity.singletexture.MIX_HoglinEntityRenderer",
    "client.entity.singletexture.MIX_HuskEntityRenderer",
    "client.entity.singletexture.MIX_IllusionerEntityRenderer",
    "client.entity.singletexture.MIX_IronGolemEntityRenderer",
    "client.entity.singletexture.MIX_MagmaCubeEntityRenderer",
    "client.entity.singletexture.MIX_OcelotEntityRenderer",
    "client.entity.singletexture.MIX_PigEntityRenderer",
    "client.entity.singletexture.MIX_PillagerEntityRenderer",
    "client.entity.singletexture.MIX_PolarBearEntityRenderer",
    "client.entity.singletexture.MIX_PufferfishEntityRenderer",
    "client.entity.singletexture.MIX_RavagerEntityRenderer",
    "client.entity.singletexture.MIX_SalmonEntityRenderer",
    "client.entity.singletexture.MIX_SheepEntityRenderer",
    "client.entity.singletexture.MIX_SilverfishEntityRenderer",
    "client.entity.singletexture.MIX_SkeletonEntityRenderer",
    "client.entity.singletexture.MIX_SlimeEntityRenderer",
    "client.entity.singletexture.MIX_SnowGolemEntityRenderer",
    "client.entity.singletexture.MIX_SpiderEntityRenderer",
    "client.entity.singletexture.MIX_SquidEntityRenderer",
    "client.entity.singletexture.MIX_StrayEntityRenderer",
    "client.entity.singletexture.MIX_TurtleEntityRenderer",
    "client.entity.singletexture.MIX_VindicatorEntityRenderer",
    "client.entity.singletexture.MIX_WanderingTraderEntityRenderer",
    "client.entity.singletexture.MIX_WitchEntityRenderer",
    "client.entity.singletexture.MIX_WitherSkeletonEntityRenderer",
    "client.entity.singletexture.MIX_ZoglinEntityRenderer",
    "client.entity.singletexture.MIX_ZombieEntityRenderer"
  ],
  "client": [
  ],
  "injectors": {
    "defaultRequire": 1
  }
}
