{
  "required": true,
  "package": "traben.entity_texture_features.mixin",
  "compatibilityLevel": "JAVA_8",
  "client": [
    "MixinIdentifier",
    "accessor.ElytraEntityModelAccessor",
    "accessor.MooshroomEntityAccessor",
    "accessor.SpriteAccessor",
    "cacheReloaders.MixinMinecraftClient",
    "cacheReloaders.MixinPlayerEntity",
    "entity.MixinLivingEntityRenderer",
    "MixinPackScreen",
    "entity.MixinPlayerEntityRenderer",
    "entity.block_entity.MixinBedBlockEntityRenderer",
    "entity.block_entity.MixinBellBlockEntityRenderer",
    "entity.block_entity.MixinChestBlockEntityRenderer",
    "entity.block_entity.MixinEnchantingTableBlockEntityRenderer",
    "entity.block_entity.MixinLecternBlockEntityRenderer",
    "entity.block_entity.MixinShulkerBoxBlockEntityRenderer",
    "entity.feature_renderers.MixinCapeFeatureRenderer",
    "entity.feature_renderers.MixinDrownedOverlayFeatureRenderer",
    "entity.feature_renderers.MixinElytraFeatureRenderer",
    "entity.feature_renderers.MixinEyesFeatureRenderer",
    "entity.feature_renderers.MixinHorseArmorFeatureRenderer",
    "entity.feature_renderers.MixinHorsemarkingFeatureRenderer",
    "entity.feature_renderers.MixinIronGolemCrackFeatureRenderer",
    "entity.feature_renderers.MixinMooshroomMushroomFeatureRenderer",
    "entity.feature_renderers.MixinSheepWoolFeatureRenderer",
    "entity.feature_renderers.MixinShoulderParrotFeatureRenderer",
    "entity.feature_renderers.MixinShulkerHeadFeatureRenderer",
    "entity.feature_renderers.MixinSlimeOverlayFeatureRenderer",
    "entity.feature_renderers.MixinVillagerClothingFeatureRenderer",
    "entity.misc.MixinAbstractClientPlayerEntity",
    "entity.misc.MixinBuiltinModelItemRenderer",
    "entity.misc.MixinElytraEntityModel",
    "entity.misc.MixinEnderDragonEntityRenderer",
    "entity.misc.MixinMobSpawnerBlockEntityRenderer",
    "entity.misc.MixinModelPart",
    "entity.misc.MixinTridentEntity",
    "entity.misc.MixinTridentEntityRenderer",
    "cacheReloaders.MixinSimpleResourceReload"
  ],
  "mixins": [

  ],
  "injectors": {
    "defaultRequire": 1
  }
}